supermaker_ai_image_master/__init__.py
supermaker_ai_image_master-1.0.1766489833.dist-info/licenses/LICENSE
supermaker_ai_image_master-1.0.1766489833.dist-info/METADATA
supermaker_ai_image_master-1.0.1766489833.dist-info/WHEEL
supermaker_ai_image_master-1.0.1766489833.dist-info/top_level.txt
supermaker_ai_image_master-1.0.1766489833.dist-info/RECORD
