Metadata-Version: 2.4
Name: supermaker-ai-image-master
Version: 1.0.1766489833
Summary: Generate branded links and HTML anchors for https://supermaker.ai/image/
Home-page: https://supermaker.ai/image/
Author: SuperMaker
Classifier: Programming Language :: Python :: 3
Classifier: License :: OSI Approved :: MIT License
Requires-Python: >=3.6
License-File: LICENSE
Dynamic: author
Dynamic: classifier
Dynamic: description
Dynamic: description-content-type
Dynamic: home-page
Dynamic: license-file
Dynamic: requires-python
Dynamic: summary
